feature_extractor/__init__.py
feature_extractor/common/DiscriminantAnalysis.py
feature_extractor/common/__init__.py
feature_extractor/common/models.py
feature_extractor/features/Extractor.py
feature_extractor/features/FeatureExtractorNaive.py
feature_extractor/features/FeatureExtractorPairsCheck.py
feature_extractor/features/FeatureExtractorWithFarawayClasses.py
feature_extractor/features/ICDA.py
feature_extractor/features/__init__.py
feature_extractor/indi/INDI.py
feature_extractor/indi/IndiBase.py
feature_extractor/indi/MulticlassINDI.py
feature_extractor/indi/__init__.py
feature_extractor/smart/SegmentAnything.py
feature_extractor/smart/SmartMINDI.py
feature_extractor/smart/__init__.py
feature_extractor/tools/__init__.py
feature_extractor/tools/tools.py
feature_extractor/tools/utils.py
informativefeatureselection-3.1.3.dist-info/licenses/LICENSE
informativefeatureselection-3.1.3.dist-info/METADATA
informativefeatureselection-3.1.3.dist-info/WHEEL
informativefeatureselection-3.1.3.dist-info/top_level.txt
informativefeatureselection-3.1.3.dist-info/RECORD
