Metadata-Version: 2.4
Name: InformativeFeatureSelection
Version: 3.1.3
Summary: Package which provides an feature selection algorithm which considers class separability and an implementation of Informative Normalized Difference Index (INDI)
Home-page: https://gitlab.com/rustam-industries/feature_extractor
Author: Mukhin Artem
Author-email: artemmukhinssau@gmail.com
License: MIT
Classifier: Programming Language :: Python :: 3
Classifier: Topic :: Software Development :: Libraries :: Python Modules
License-File: LICENSE
Requires-Dist: numpy~=1.21
Requires-Dist: scikit-learn~=0.24.2
Requires-Dist: setuptools~=58.0.4
Requires-Dist: opencv-python-headless~=4.5.3.56
Requires-Dist: numba~=0.57.1
Provides-Extra: smart
Requires-Dist: segment_anything==1.0; extra == "smart"
Dynamic: author
Dynamic: author-email
Dynamic: classifier
Dynamic: description
Dynamic: description-content-type
Dynamic: home-page
Dynamic: license
Dynamic: license-file
Dynamic: provides-extra
Dynamic: requires-dist
Dynamic: summary
